sentigpt/__init__.py
sentigpt/aimanager.py
sentigpt/sentimentmanager.py
sentigpt/textanalysis.py
sentigpt-0.143.dist-info/METADATA
sentigpt-0.143.dist-info/WHEEL
sentigpt-0.143.dist-info/top_level.txt
sentigpt-0.143.dist-info/RECORD
